{
  "files_created": [
    "src/components/ui/GlowCard.tsx",
    "src/components/sections/Features.tsx"
  ],
  "files_modified": [
    "src/App.tsx"
  ],
  "decisions": [
    {
      "what": "Used named export for GlowCard with ReactNode/className props and added aria-hidden to decorative gradient layers.",
      "why": "Spec requested named export and decorative layers should not be exposed to assistive tech."
    },
    {
      "what": "Used '@/' alias imports in Features.tsx for ScrollReveal and GlowCard.",
      "why": "vite.config.ts and existing components like MorphingButton consistently use the '@/' alias for src imports."
    },
    {
      "what": "Assigned feature.icon to a capitalized local Icon variable inside the map.",
      "why": "JSX requires capitalized identifiers for component types; lowercase 'feature.icon' would render as a DOM tag."
    },
    {
      "what": "Default-exported Features and rendered it directly after Hero inside main.",
      "why": "Spec required default export and structure: Header > main > Hero > Features."
    }
  ],
  "tools_used": [
    "Read",
    "Write",
    "Edit"
  ]
}
