{
  "files_created": [
    ".env.example",
    "src/config/web3.ts",
    "src/components/providers/Web3Provider.tsx"
  ],
  "files_modified": [
    "src/main.tsx"
  ],
  "decisions": [
    {
      "what": "Used getDefaultConfig from @rainbow-me/rainbowkit for wagmi setup",
      "why": "Specification explicitly requires getDefaultConfig with appName, projectId, and chains; it auto-includes MetaMask, WalletConnect, and Coinbase Wallet connectors via RainbowKit defaults."
    },
    {
      "what": "Added `as const` to chains tuple in src/config/web3.ts",
      "why": "Preserves precise tuple typing for wagmi/RainbowKit which expects a readonly non-empty chain tuple."
    },
    {
      "what": "Set ssr: false on the wagmi config",
      "why": "This is a Vite SPA (no SSR); explicit flag avoids hydration-related warnings from getDefaultConfig defaults."
    },
    {
      "what": "Created QueryClient as a module-level singleton in Web3Provider.tsx",
      "why": "Specification requires the QueryClient to be created once at module scope so it isn't re-created on every render."
    },
    {
      "what": "Configured darkTheme with accentColor #8b5cf6, accentColorForeground white, borderRadius 'medium'",
      "why": "Matches the app accent color from tailwind.config.ts and the explicit RainbowKit theme parameters in the specification."
    },
    {
      "what": "Wrapped <App /> with <Web3Provider> inside <StrictMode> in src/main.tsx",
      "why": "Specification mandates the provider hierarchy StrictMode > Web3Provider > App so wagmi/RainbowKit context is available throughout the tree."
    }
  ],
  "tools_used": [
    "Read",
    "Write",
    "Edit"
  ]
}
